carterpy/__init__.py
carterpy/async_carter.py
carterpy/carter.py
carterpy/classes.py
carterpy/utils.py
carter_py-1.0.2.dist-info/METADATA
carter_py-1.0.2.dist-info/WHEEL
carter_py-1.0.2.dist-info/license.txt
carter_py-1.0.2.dist-info/top_level.txt
carter_py-1.0.2.dist-info/RECORD
