Metadata-Version: 2.1
Name: carter-py
Version: 1.0.2
Summary: A wrapper for the Carter API
Home-page: https://github.com/LazyLyrics/carter-py
Author: LazyLyrics
Author-email: lazylyrics@icloud.com
Classifier: Development Status :: 3 - Alpha
Classifier: Intended Audience :: Developers
Classifier: License :: OSI Approved :: MIT License
Classifier: Programming Language :: Python :: 3
Classifier: Programming Language :: Python :: 3.6
Classifier: Programming Language :: Python :: 3.7
Classifier: Programming Language :: Python :: 3.8
Classifier: Programming Language :: Python :: 3.9
License-File: license.txt
Requires-Dist: aiohttp (==3.8.4)
Requires-Dist: aioresponses (==0.7.4)
Requires-Dist: asynctest (==0.13.0)
Requires-Dist: python-dotenv (==1.0.0)
Requires-Dist: Requests (==2.28.2)
Requires-Dist: responses (==0.23.1)
Requires-Dist: setuptools (==65.5.0)
